hairydogm/__init__.py
hairydogm/chat_action.py
hairydogm/keyboard.py
hairydogm/mixins.py
hairydogm/filters/__init__.py
hairydogm/filters/callback_data.py
hairydogm/i18n/__init__.py
hairydogm/i18n/context.py
hairydogm/i18n/core.py
hairydogm-0.4.1.dist-info/METADATA
hairydogm-0.4.1.dist-info/WHEEL
hairydogm-0.4.1.dist-info/licenses/LICENSE
hairydogm-0.4.1.dist-info/RECORD
