Metadata-Version: 2.3
Name: hairydogm
Version: 0.4.1
Summary: Some utilities from AIOgram adapted to be used with Hydrogram.
Project-URL: homepage, https://github.com/HitaloM/hairydogm
Project-URL: tracker, https://github.com/HitaloM/hairydogm/issues
Project-URL: community, https://t.me/HitaloProjects
Project-URL: source, https://github.com/HitaloM/hairydogm
Project-URL: documentation, https://hairydogm.readthedocs.io/
Author: Hitalo
License: Copyright (c) 2024-present Hitalo M
License-File: LICENSE
Keywords: aiogram,asyncio,bot,hairydogm,hydrogram,telegram
Classifier: Development Status :: 5 - Production/Stable
Classifier: Environment :: Console
Classifier: Intended Audience :: Developers
Classifier: License :: OSI Approved :: MIT License
Classifier: Operating System :: OS Independent
Classifier: Programming Language :: Python :: 3 :: Only
Classifier: Programming Language :: Python :: 3.12
Classifier: Programming Language :: Python :: Implementation :: CPython
Classifier: Topic :: Software Development :: Libraries :: Python Modules
Classifier: Topic :: Utilities
Requires-Python: >=3.12
Requires-Dist: babel>=2.15.0
Requires-Dist: hydrogram>=0.1.4
Requires-Dist: magic-filter>=1.0.12
Requires-Dist: pydantic>=2.7.1
